harm_analysis-1.3.0.dist-info/METADATA
harm_analysis-1.3.0.dist-info/WHEEL
harm_analysis-1.3.0.dist-info/entry_points.txt
harm_analysis-1.3.0.dist-info/licenses/LICENSE
harm_analysis/__init__.py
harm_analysis/_harm_analysis.py
harm_analysis/cli.py
harm_analysis-1.3.0.dist-info/RECORD
