Metadata-Version: 2.1
Name: harm-analysis
Version: 1.3.0
Summary: A Python library to estimate parameters from a signal containing a tone.
Keywords: DSP,Signal-Processing,THD,SNR
Author-Email: Eric Macedo <ericsmacedo@gmail.com>
Classifier: Programming Language :: Python :: 3
Classifier: Programming Language :: Python :: 3.10
Classifier: Programming Language :: Python :: 3.11
Classifier: Programming Language :: Python :: 3.12
Classifier: Programming Language :: Python :: 3.13
Classifier: Operating System :: OS Independent
Project-URL: Homepage, https://github.com/ericsmacedo/harm-analysis
Project-URL: Documentation, https://harm-analysis.readthedocs.io/en/stable/
Project-URL: Bug Tracker, https://github.com/ericsmacedo/harm-analysis/issues
Requires-Python: <4.0,>=3.10.0
Requires-Dist: click>=8.2.1
Requires-Dist: matplotlib>=3.10.3
Requires-Dist: numpy>=2.2.6
Requires-Dist: rich>=14.1.0
Requires-Dist: scipy>=1.15.3
